{"nodes": [{"id": "comp_buttons", "label": "Buttons Component Family", "file_type": "document", "source_file": "preview/components-buttons.html", "source_location": null, "source_url": null, "captured_at": null, "author": null, "contributor": null}, {"id": "btn_primary", "label": "Primary Button (.btn-primary)", "file_type": "document", "source_file": "preview/components-buttons.html", "source_location": "lines 8-16", "source_url": null, "captured_at": null, "author": null, "contributor": null}, {"id": "btn_ghost", "label": "Ghost Button (.btn-ghost)", "file_type": "document", "source_file": "preview/components-buttons.html", "source_location": "lines 17-27", "source_url": null, "captured_at": null, "author": null, "contributor": null}, {"id": "btn_dashed", "label": "Dashed Button (.btn-dashed)", "file_type": "document", "source_file": "preview/components-buttons.html", "source_location": "lines 28-40", "source_url": null, "captured_at": null, "author": null, "contributor": null}, {"id": "btn_danger", "label": "Danger Button (.btn-danger)", "file_type": "document", "source_file": "preview/components-buttons.html", "source_location": "lines 41-51", "source_url": null, "captured_at": null, "author": null, "contributor": null}, {"id": "btn_icon", "label": "Icon Button (.btn-icon)", "file_type": "document", "source_file": "preview/components-buttons.html", "source_location": "lines 52-59", "source_url": null, "captured_at": null, "author": null, "contributor": null}, {"id": "token_color_violet", "label": "Brand Violet #7c6af7", "file_type": "document", "source_file": "preview/components-buttons.html", "source_location": null, "source_url": null, "captured_at": null, "author": null, "contributor": null}, {"id": "token_color_pink", "label": "Danger Pink #f76a8c", "file_type": "document", "source_file": "preview/components-buttons.html", "source_location": null, "source_url": null, "captured_at": null, "author": null, "contributor": null}, {"id": "token_color_bg_alt", "label": "Alt Surface #1a1a26", "file_type": "document", "source_file": "preview/components-buttons.html", "source_location": null, "source_url": null, "captured_at": null, "author": null, "contributor": null}, {"id": "token_radius_button", "label": "Button Radius 6-8px", "file_type": "document", "source_file": "preview/components-buttons.html", "source_location": null, "source_url": null, "captured_at": null, "author": null, "contributor": null}, {"id": "token_font_display", "label": "Font Display (var(--font-display) / Syne)", "file_type": "document", "source_file": "preview/components-buttons.html", "source_location": null, "source_url": null, "captured_at": null, "author": null, "contributor": null}, {"id": "token_font_mono", "label": "Font Mono (var(--font-mono))", "file_type": "document", "source_file": "preview/components-buttons.html", "source_location": null, "source_url": null, "captured_at": null, "author": null, "contributor": null}], "edges": [{"source": "btn_primary", "target": "comp_buttons", "relation": "implements", "confidence": "EXTRACTED", "confidence_score": 1.0, "source_file": "preview/components-buttons.html", "source_location": null, "weight": 1.0}, {"source": "btn_ghost", "target": "comp_buttons", "relation": "implements", "confidence": "EXTRACTED", "confidence_score": 1.0, "source_file": "preview/components-buttons.html", "source_location": null, "weight": 1.0}, {"source": "btn_dashed", "target": "comp_buttons", "relation": "implements", "confidence": "EXTRACTED", "confidence_score": 1.0, "source_file": "preview/components-buttons.html", "source_location": null, "weight": 1.0}, {"source": "btn_danger", "target": "comp_buttons", "relation": "implements", "confidence": "EXTRACTED", "confidence_score": 1.0, "source_file": "preview/components-buttons.html", "source_location": null, "weight": 1.0}, {"source": "btn_icon", "target": "comp_buttons", "relation": "implements", "confidence": "EXTRACTED", "confidence_score": 1.0, "source_file": "preview/components-buttons.html", "source_location": null, "weight": 1.0}, {"source": "btn_primary", "target": "token_color_violet", "relation": "references", "confidence": "EXTRACTED", "confidence_score": 1.0, "source_file": "preview/components-buttons.html", "source_location": "line 9", "weight": 1.0}, {"source": "btn_primary", "target": "token_font_display", "relation": "references", "confidence": "EXTRACTED", "confidence_score": 1.0, "source_file": "preview/components-buttons.html", "source_location": "line 7", "weight": 1.0}, {"source": "btn_ghost", "target": "token_font_mono", "relation": "references", "confidence": "EXTRACTED", "confidence_score": 1.0, "source_file": "preview/components-buttons.html", "source_location": "line 24", "weight": 1.0}, {"source": "btn_ghost", "target": "token_color_bg_alt", "relation": "references", "confidence": "EXTRACTED", "confidence_score": 1.0, "source_file": "preview/components-buttons.html", "source_location": "line 18", "weight": 1.0}, {"source": "btn_danger", "target": "token_color_pink", "relation": "references", "confidence": "EXTRACTED", "confidence_score": 1.0, "source_file": "preview/components-buttons.html", "source_location": "line 43", "weight": 1.0}, {"source": "btn_dashed", "target": "token_color_bg_alt", "relation": "references", "confidence": "EXTRACTED", "confidence_score": 1.0, "source_file": "preview/components-buttons.html", "source_location": "line 29", "weight": 1.0}], "hyperedges": [{"id": "button_family", "label": "Button Variant Family", "nodes": ["btn_primary", "btn_ghost", "btn_dashed", "btn_danger", "btn_icon"], "relation": "form", "confidence": "EXTRACTED", "confidence_score": 1.0, "source_file": "preview/components-buttons.html"}]}